ibuffpy/ReactionNetwork.py
ibuffpy/__init__.py
ibuffpy/massaction.py
ibuffpy/ftn/__init__.py
ibuffpy/ftn/ftn_compute_bs_meansmat.py
ibuffpy/ftn/ftn_compute_nullspace.py
ibuffpy/ftn/ftn_compute_smat.py
ibuffpy/ftn/ftn_make_hiergraph.py
ibuffpy-0.1.0.dist-info/LICENSE
ibuffpy-0.1.0.dist-info/METADATA
ibuffpy-0.1.0.dist-info/WHEEL
ibuffpy-0.1.0.dist-info/top_level.txt
ibuffpy-0.1.0.dist-info/RECORD
