Metadata-Version: 2.1
Name: ibuffpy
Version: 0.1.0
Summary: A Python package for appling Structural Sensitivity Analysis to reaction networks.
Home-page: https://github.com/hishidagit/SSApy
Author: Atsuki Hishida
Author-email: ahishida18@gmail.com
License: MIT
Project-URL: Homepage, https://github.com/hishidagit/SSApy
Project-URL: Bug Tracker, https://github.com/hishidagit/SSApy/issues
Classifier: Programming Language :: Python :: 3
Classifier: License :: OSI Approved :: MIT License
Classifier: Operating System :: OS Independent
Requires-Python: >=3.8
License-File: LICENSE
Requires-Dist: numpy >=1.23.5
Requires-Dist: scipy >=1.10.1
Requires-Dist: matplotlib >=3.7.3
Requires-Dist: pandas >=1.5.3
Requires-Dist: tqdm >=4.66.1
Requires-Dist: sympy >=1.12
Requires-Dist: networkx >=3.1
Requires-Dist: scikit-learn >=1.3.1
